README.rst
setup.cfg
setup.py
countertype/__init__.py
countertype/counter_type.py
countertype/counter_type_registration.py
countertype/py.typed
countertype.egg-info/PKG-INFO
countertype.egg-info/SOURCES.txt
countertype.egg-info/dependency_links.txt
countertype.egg-info/top_level.txt
test/__init__.py
test/test_counter_type.py