Metadata-Version: 1.0
Name: countertype
Version: 1.2.1
Summary: countertype
Home-page: UNKNOWN
Author: Bogdan Mustiata
Author-email: bogdan.mustiata@gmail.com
License: BSD
Platform: UNKNOWN
